pumaz/__init__.py
pumaz/constants.py
pumaz/display.py
pumaz/download.py
pumaz/file_utilities.py
pumaz/image_conversion.py
pumaz/image_processing.py
pumaz/input_validation.py
pumaz/pumaz.py
pumaz/resources.py
pumaz-1.8.11.dist-info/licenses/LICENSE
pumaz-1.8.11.dist-info/METADATA
pumaz-1.8.11.dist-info/WHEEL
pumaz-1.8.11.dist-info/entry_points.txt
pumaz-1.8.11.dist-info/top_level.txt
pumaz-1.8.11.dist-info/RECORD
