Metadata-Version: 2.4
Name: pumaz
Version: 1.8.11
Summary: PUMA (PET Universal Multi-tracer Aligner) aligns multi-tracer PET/CT studies using advanced diffeomorphic imaging.
Author-email: Lalith Kumar Shiyam Sundar <Lalith.shiyamsundar@meduniwien.ac.at>, Sebastian Gutschmayer <Sebastian.Gutschmayer@meduniwien.ac.at>, Manuel Pires <Manuel.pires@meduniwien.ac.at>
License:                     GNU GENERAL PUBLIC LICENSE
Project-URL: Homepage, https://github.com/QIMP-Team/PUMA
Keywords: PET tracer alignment,diffeomorphic imaging,image processing,multiplexed tracers
Classifier: Development Status :: 4 - Beta
Classifier: Intended Audience :: Developers
Classifier: Intended Audience :: Healthcare Industry
Classifier: License :: OSI Approved :: GNU General Public License v3 (GPLv3)
Classifier: Programming Language :: Python :: 3
Classifier: Programming Language :: Python :: 3 :: Only
Classifier: Programming Language :: Python :: 3.10
Classifier: Topic :: Scientific/Engineering :: Medical Science Apps.
Requires-Python: >=3.10
License-File: LICENSE
Requires-Dist: nibabel
Requires-Dist: halo
Requires-Dist: SimpleITK
Requires-Dist: pydicom
Requires-Dist: numpy
Requires-Dist: mpire
Requires-Dist: openpyxl
Requires-Dist: matplotlib
Requires-Dist: pyfiglet
Requires-Dist: natsort
Requires-Dist: colorama
Requires-Dist: rich
Requires-Dist: pandas
Requires-Dist: dicom2nifti
Requires-Dist: nifti2dicom
Requires-Dist: requests
Requires-Dist: moosez==3.0.30
Requires-Dist: emoji
Requires-Dist: click
Requires-Dist: rich-click
Requires-Dist: cfonts
Requires-Dist: psutil
Requires-Dist: gputil
Requires-Dist: dask
Dynamic: license-file
